{
  "preRequisites:9": {
    "0:10": {
      "questIDHigh:4": -7666757284599281048,
      "questIDLow:4": -5834519268653947260
    },
    "1:10": {
      "questIDHigh:4": -8173475821776908983,
      "questIDLow:4": -8724678333612648124
    }
  },
  "properties:10": {
    "betterquesting:10": {
      "autoClaim:1": 0,
      "desc:8": "Looking for ores can be difficult, but with a sluice I can gather the trace amount of ores in gravel.",
      "globalShare:1": 0,
      "icon:10": {
        "Count:3": 1,
        "Damage:2": 0,
        "OreDict:8": "",
        "id:8": "terrafirmacraft:item.SluiceItem"
      },
      "isMain:1": 0,
      "isSilent:1": 0,
      "lockedProgress:1": 0,
      "name:8": "Alternative for ores",
      "questLogic:8": "AND",
      "repeatTime:3": -1,
      "repeat_relative:1": 1,
      "simultaneous:1": 0,
      "snd_complete:8": "random.levelup",
      "snd_update:8": "random.levelup",
      "taskLogic:8": "AND",
      "visibility:8": "NORMAL"
    }
  },
  "questIDHigh:4": -1581126755776446456,
  "questIDLow:4": -5928475565452071482,
  "rewards:9": {
    "0:10": {
      "ignoreDisabled:1": 0,
      "index:3": 0,
      "rewardID:8": "bq_standard:item",
      "rewards:9": {
        "0:10": {
          "Count:3": 12,
          "Damage:2": 0,
          "OreDict:8": "",
          "id:8": "terrafirmacraft:item.Small Ore"
        }
      }
    }
  },
  "tasks:9": {
    "0:10": {
      "autoConsume:1": 0,
      "consume:1": 0,
      "groupDetect:1": 0,
      "ignoreNBT:1": 1,
      "index:3": 0,
      "partialMatch:1": 1,
      "requiredItems:9": {
        "0:10": {
          "Count:3": 1,
          "Damage:2": 0,
          "OreDict:8": "",
          "id:8": "terrafirmacraft:item.SluiceItem"
        }
      },
      "taskID:8": "bq_standard:retrieval"
    }
  }
}